MANIFEST.in
README.md
setup.cfg
setup.py
UTMDriver/__init__.py
UTMDriver/connector.py
UTMDriver.egg-info/PKG-INFO
UTMDriver.egg-info/SOURCES.txt
UTMDriver.egg-info/dependency_links.txt
UTMDriver.egg-info/requires.txt
UTMDriver.egg-info/top_level.txt
UTMDriver/generic/__init__.py
UTMDriver/generic/exceptions.py
UTMDriver/generic/documents/__init__.py
UTMDriver/generic/documents/certificate.py
UTMDriver/generic/documents/NATTN/NATTN.py
UTMDriver/generic/documents/NATTN/Position.py
UTMDriver/generic/documents/NATTN/__init__.py
UTMDriver/generic/documents/rests/__init__.py
UTMDriver/generic/documents/rests/rest.py
UTMDriver/generic/documents/rests/shopRest.py
UTMDriver/generic/documents/rests/storeRest.py
UTMDriver/generic/documents/tickets/EGAISTickets.py
UTMDriver/generic/documents/tickets/Ticket.py
UTMDriver/generic/documents/tickets/UTMTickets.py
UTMDriver/generic/documents/tickets/__init__.py
UTMDriver/generic/documents/waybill/__init__.py
UTMDriver/generic/documents/waybill/form2reginfo.py
UTMDriver/generic/documents/waybill/ttnHistoryF2Reg.py
UTMDriver/generic/documents/waybill/waybill.py
UTMDriver/generic/documents/waybill/waybill_v3.py
UTMDriver/generic/helpers/__init__.py
UTMDriver/generic/helpers/positions.py
UTMDriver/generic/helpers/textTransform.py
UTMDriver/generic/queries/__init__.py
UTMDriver/generic/queries/documents/DocRequest.py
UTMDriver/generic/queries/documents/__init__.py
UTMDriver/generic/queries/documents/templates/ActWriteOfShop_v2.xml
UTMDriver/generic/queries/documents/templates/QueryNATTN.xml
UTMDriver/generic/queries/documents/templates/QueryResendDoc.xml
UTMDriver/generic/queries/documents/templates/QueryRests.xml
UTMDriver/generic/queries/documents/templates/QueryRestsShop_v2.xml
UTMDriver/generic/queries/documents/templates/TransferToShop.xml
UTMDriver/generic/queries/documents/templates/WayBillAct_v3.xml
UTMDriver/generic/queries/documents/templates/WriteOfShop_v2.xml
UTMDriver/generic/queries/documents/templates/__init__.py
UTMDriver/generic/queries/utm/__init__.py
UTMDriver/generic/queries/utm/requests.py