Metadata-Version: 1.0
Name: UTMDriver
Version: 0.5.2a0
Summary: UTMDriver for EGAIS
Home-page: https://github.com/maxpoint2point/UTMDriver
Author: Максим
Author-email: maxpoint2point@gmail.com
License: Apache-2.0 License
Platform: UNKNOWN
